djangocms_render_context/__init__.py
djangocms_render_context/cache.py
djangocms_render_context/cms_plugins.py
djangocms_render_context/exceptions.py
djangocms_render_context/forms.py
djangocms_render_context/loaders.py
djangocms_render_context/models.py
djangocms_render_context/utils.py
djangocms_render_context/locale/cs/LC_MESSAGES/django.mo
djangocms_render_context/locale/cs/LC_MESSAGES/django.po
djangocms_render_context/migrations/0001_initial.py
djangocms_render_context/migrations/0002_rendercontext_mimetype.py
djangocms_render_context/migrations/__init__.py
djangocms_render_context-1.1.0.dist-info/METADATA
djangocms_render_context-1.1.0.dist-info/WHEEL
djangocms_render_context-1.1.0.dist-info/top_level.txt
djangocms_render_context-1.1.0.dist-info/RECORD
